ballotpedia/__init__.py
ballotpedia/api.py
ballotpedia/api_types.py
ballotpedia-0.1.2.dist-info/LICENSE.txt
ballotpedia-0.1.2.dist-info/METADATA
ballotpedia-0.1.2.dist-info/WHEEL
ballotpedia-0.1.2.dist-info/top_level.txt
ballotpedia-0.1.2.dist-info/RECORD
