Metadata-Version: 2.1
Name: ballotpedia
Version: 0.1.2
Summary: Add a short description here!
Home-page: https://github.com/pyscaffold/pyscaffold/
Author: Brian Seel
Author-email: brian.seel@gmail.com
License: MIT
Project-URL: Documentation, https://pyscaffold.org/
Platform: any
Classifier: Development Status :: 4 - Beta
Classifier: Programming Language :: Python
License-File: LICENSE.txt
Requires-Dist: requests
Requires-Dist: importlib-metadata ; python_version < "3.8"
Provides-Extra: testing
Requires-Dist: setuptools ; extra == 'testing'
Requires-Dist: pytest ; extra == 'testing'
Requires-Dist: pytest-cov ; extra == 'testing'
Requires-Dist: requests-mock ; extra == 'testing'
Requires-Dist: typing-extensions ; extra == 'testing'
